{
  "ui_prompt": {
    "idea": "Project: ",
    "type": "",
    "technologies": ["Next.js", "Tailwind CSS", "JavaScript"],
    "Route": "nextjs app route",
    "design": {
      "layout": "",
      "components": [],
      "additional": ""
    },
    "order": [
      "setup project with Next.js and Tailwind CSS",
      "create homepage with link to main content page",
      "create main content page component",
      "load data from JSON in public folder | import , Not fetch",
      "display sections with headings, paragraphs, timeline or list",
      "add responsive Tailwind CSS styles",
      "ensure 100% responsive design for all devices: mobile, tablet, vertical screens, wide screens, and large desktop monitors"
    ],
    "instructions": {
      "output": "write code only",
      "format": "no explanation, no comments, just raw code",
      "include": "at the top of output, show file/folder list (most of the time use .jsx _ not .js | if you use big/medium data: create json, not object | keep JSON in public folder"
    }
  }
}